re2c/__init__.py
re2c/_version.py
re2c/data/bin/re2c.exe
re2c/data/share/man/man1/re2c.1
re2c/data/share/re2c/stdlib/c
re2c/data/share/re2c/stdlib/d
re2c/data/share/re2c/stdlib/go
re2c/data/share/re2c/stdlib/haskell
re2c/data/share/re2c/stdlib/java
re2c/data/share/re2c/stdlib/js
re2c/data/share/re2c/stdlib/ocaml
re2c/data/share/re2c/stdlib/python
re2c/data/share/re2c/stdlib/rust
re2c/data/share/re2c/stdlib/unicode_categories.re
re2c/data/share/re2c/stdlib/v
re2c/data/share/re2c/stdlib/zig
re2c-4.0.dist-info/METADATA
re2c-4.0.dist-info/WHEEL
re2c-4.0.dist-info/entry_points.txt
re2c-4.0.dist-info/RECORD
