Metadata-Version: 2.1
Name: re2c
Version: 4.0
Summary: re2c is a free and open-source lexer generator for C, C++, D, Go, Haskell, Java, JS, OCaml, Python, Rust, V and Zig with a focus on generating fast code.
Keywords: re2c,build,c,c++,d,go,haskell,java,js,ocaml,python,rust,v,zig
License: https://github.com/skvadrik/re2c/blob/master/LICENSE
Classifier: License :: Public Domain
Classifier: Programming Language :: C
Classifier: Programming Language :: C++
Classifier: Programming Language :: D
Classifier: Programming Language :: Go
Classifier: Programming Language :: Haskell
Classifier: Programming Language :: Java
Classifier: Programming Language :: JavaScript
Classifier: Programming Language :: OCaml
Classifier: Programming Language :: Python
Classifier: Programming Language :: Rust
Classifier: Operating System :: MacOS :: MacOS X
Classifier: Operating System :: Microsoft :: Windows
Classifier: Operating System :: POSIX :: Linux
Classifier: Development Status :: 5 - Production/Stable
Classifier: Intended Audience :: Developers
Classifier: Topic :: Software Development :: Build Tools
Classifier: Topic :: Software Development :: Code Generators
Classifier: Topic :: Software Development :: Pre-processors
Project-URL: Homepage, https://re2c.org/
Project-URL: Source code, https://github.com/skvadrik/re2c
Project-URL: Bug tracker, https://github.com/skvadrik/re2c/issues
